py/.DS_Store
py/__init__.py
py/zconfig/.DS_Store
py/zconfig/DB/__init__.py
py/zconfig/DB/nutdb.json
py/zconfig/NUT_DB_REGIONS_URL.txt
py/zconfig/NUT_DB_REGIONS_URL_MIRROR.txt
py/zconfig/NUT_DB_URL.txt
py/zconfig/NUT_DB_URL_mirror.txt
py/zconfig/__init__.py
py/zconfig/download_libraries_example.txt
py/zconfig/local_libraries_example.txt
py/zconfig/mtp_SD_libraries_example.txt
py/zconfig/mtp_download_libraries_example.txt
py/zconfig/mtp_source_libraries_example.txt
py/zconfig/mtp_xci_locations.txt
py/zconfig/remote_cache_location_example.txt
py/zconfig/remote_libraries_example.txt
py/ztools/.DS_Store
py/ztools/Drive/Decompress.py
py/ztools/Drive/Download.py
py/ztools/Drive/DriveHtmlInfo.py
py/ztools/Drive/DriveTools.py
py/ztools/Drive/Info.py
py/ztools/Drive/Private.py
py/ztools/Drive/Public.py
py/ztools/Drive/Upload.py
py/ztools/Drive/XciTools.py
py/ztools/Drive/__init__.py
py/ztools/Drive/fichier.py
py/ztools/Drive/service.py
py/ztools/Fs/BaseFs.py
py/ztools/Fs/Bktr.py
py/ztools/Fs/ChromeNacp.py
py/ztools/Fs/ChromeNca.py
py/ztools/Fs/ChromeNsp.py
py/ztools/Fs/ChromeXci.py
py/ztools/Fs/Cnmt.py
py/ztools/Fs/File.py
py/ztools/Fs/Hfs0.py
py/ztools/Fs/Ivfc.py
py/ztools/Fs/Nacp.py
py/ztools/Fs/Nca.py
py/ztools/Fs/Nsp.py
py/ztools/Fs/Pfs0.py
py/ztools/Fs/Rom.py
py/ztools/Fs/Ticket.py
py/ztools/Fs/Titles.py
py/ztools/Fs/Type.py
py/ztools/Fs/Xci.py
py/ztools/Fs/__init__.py
py/ztools/Fs/lib/Config.py
py/ztools/Fs/lib/CryptoUtils.py
py/ztools/Fs/lib/DBmodule.py
py/ztools/Fs/lib/File_chunk.py
py/ztools/Fs/lib/File_chunk2.py
py/ztools/Fs/lib/Hex.py
py/ztools/Fs/lib/Interface.py
py/ztools/Fs/lib/Keys.py
py/ztools/Fs/lib/NXKeys.py
py/ztools/Fs/lib/Nsps.py
py/ztools/Fs/lib/Print.py
py/ztools/Fs/lib/Status.py
py/ztools/Fs/lib/Title.py
py/ztools/Fs/lib/Titles.py
py/ztools/Fs/lib/Utils.py
py/ztools/Fs/lib/__init__.py
py/ztools/Fs/lib/aes128.py
py/ztools/Fs/lib/batchprocess.py
py/ztools/Fs/lib/blockchain.py
py/ztools/Fs/lib/compressor.py
py/ztools/Fs/lib/decompressor.py
nstool-1.1.2.dist-info/LICENSE
nstool-1.1.2.dist-info/METADATA
nstool-1.1.2.dist-info/WHEEL
nstool-1.1.2.dist-info/entry_points.txt
nstool-1.1.2.dist-info/RECORD
