Metadata-Version: 2.1
Name: nstool
Version: 1.1.2
Summary: nstool
Home-page: https://github.com/julesontheroad
License: MIT
Keywords: ns,tool
Author: julesontheroad
Author-email: julesontheroad@gmail.com
Requires-Python: >=3.9,<4
Classifier: License :: OSI Approved :: MIT License
Classifier: Operating System :: MacOS
Classifier: Operating System :: Microsoft :: Windows
Classifier: Programming Language :: Python :: 3
Classifier: Programming Language :: Python :: 3.9
Classifier: Programming Language :: Python :: 3.10
Classifier: Programming Language :: Python :: 3.11
Classifier: Programming Language :: Python :: 3.10
Classifier: Topic :: Utilities
Requires-Dist: bottle (>=0.12.25,<0.13.0)
Requires-Dist: bs4 (>=0.0.1,<0.0.2)
Requires-Dist: chardet (>=3.0.4,<4.0.0)
Requires-Dist: colorama (>=0.4.6,<0.5.0)
Requires-Dist: comtypes (>=1.1.14,<2.0.0)
Requires-Dist: eel (>=0.16.0,<0.17.0)
Requires-Dist: google-auth-httplib2 (>=0.1.0,<0.2.0)
Requires-Dist: google-auth-oauthlib (>=1.0.0,<2.0.0)
Requires-Dist: googletrans (>=3.0.0,<4.0.0)
Requires-Dist: httpx (==0.13.3)
Requires-Dist: image (>=1.5.33,<2.0.0)
Requires-Dist: oauth2client (>=4.1.3,<5.0.0)
Requires-Dist: pycryptodome (>=3.17,<4.0)
Requires-Dist: pykakasi (>=2.2.1,<3.0.0)
Requires-Dist: requests (>=2.28.2,<3.0.0)
Requires-Dist: tqdm (>=4.65.0,<5.0.0)
Requires-Dist: unidecode (>=1.3.6,<2.0.0)
Requires-Dist: urllib3 (>=1.26.14,<2.0.0)
Requires-Dist: zstandard (>=0.20.0,<0.21.0)
Project-URL: Repository, https://github.com/julesontheroad/NSC_BUILDER
